bboptpy.cp312-win_amd64.pyd
cocoaopt.cp312-win_amd64.pyd
bboptpy-0.1.dist-info/LICENSE
bboptpy-0.1.dist-info/METADATA
bboptpy-0.1.dist-info/WHEEL
bboptpy-0.1.dist-info/top_level.txt
bboptpy-0.1.dist-info/RECORD
