Metadata-Version: 2.1
Name: bboptpy
Version: 0.1
Summary: Powerful and scalable black-box optimization algorithms for Python and C++.
Home-page: https://github.com/mike-gimelfarb/bboptpy
Author: Michael Gimelfarb
Author-email: mgimelfarb@yahoo.ca
License: LGPL-2.1 License
Classifier: Development Status :: 4 - Beta
Classifier: Intended Audience :: Science/Research
Classifier: License :: OSI Approved :: MIT License
Classifier: Natural Language :: English
Classifier: Operating System :: OS Independent
Classifier: Programming Language :: Python :: 3
Classifier: Topic :: Scientific/Engineering :: Artificial Intelligence
Requires-Python: >=3.8
License-File: LICENSE
Requires-Dist: pybind11>=2.11.1
Requires-Dist: numpy
